smartetailing/__init__.py
smartetailing/__serializer.py
smartetailing/connection.py
smartetailing/objects.py
smartetailing-0.4.5.dist-info/LICENSE
smartetailing-0.4.5.dist-info/METADATA
smartetailing-0.4.5.dist-info/WHEEL
smartetailing-0.4.5.dist-info/top_level.txt
smartetailing-0.4.5.dist-info/RECORD
