Metadata-Version: 2.1
Name: smartetailing
Version: 0.4.5
Summary: Connect to the smartetailing website order feeds
Home-page: https://github.com/fundthmcalculus/smartetailing
Author: Scott Phillips
Author-email: polygonguru@gmail.com
License: MIT
Platform: UNKNOWN
Classifier: License :: OSI Approved :: MIT License
Classifier: Programming Language :: Python :: 3
Classifier: Programming Language :: Python :: 3.8
License-File: LICENSE
Requires-Dist: lxml
Requires-Dist: requests
Requires-Dist: urllib3
Requires-Dist: beautifulsoup4
Requires-Dist: pyap
